README.md
setup.py
decorate_all_methods/__init__.py
decorate_all_methods.egg-info/PKG-INFO
decorate_all_methods.egg-info/SOURCES.txt
decorate_all_methods.egg-info/dependency_links.txt
decorate_all_methods.egg-info/top_level.txt