Metadata-Version: 1.0
Name: decorate-all-methods
Version: 0.0.1
Summary: a class decorator that applies to all methods
Home-page: https://github.com/davegallant/decorate_all_methods
Author: Dave Gallant
Author-email: davegallant@gmail.com
License: Apache License, Version 2.0
Keywords: python,decorator
Platform: UNKNOWN
